aequitas/__init__.py
aequitas/bias.py
aequitas/fairness.py
aequitas/group.py
aequitas/plotting.py
aequitas/preprocessing.py
aequitas/squarify_flipped.py
aequitas/plot/__init__.py
aequitas/plot/bubble_concatenation_chart.py
aequitas/plot/bubble_disparity_chart.py
aequitas/plot/bubble_metric_chart.py
aequitas/plot/summary_chart.py
aequitas/plot/xy_metrics_chart.py
aequitas/plot/commons/__init__.py
aequitas/plot/commons/helpers.py
aequitas/plot/commons/initializers.py
aequitas/plot/commons/labels.py
aequitas/plot/commons/legend.py
aequitas/plot/commons/scales.py
aequitas/plot/commons/tooltips.py
aequitas/plot/commons/validators.py
aequitas/plot/commons/style/__init__.py
aequitas/plot/commons/style/classes.py
aequitas/plot/commons/style/color.py
aequitas/plot/commons/style/sizes.py
aequitas/plot/commons/style/text.py
aequitas_lite-0.43.5.dist-info/AUTHORS.rst
aequitas_lite-0.43.5.dist-info/LICENSE
aequitas_lite-0.43.5.dist-info/METADATA
aequitas_lite-0.43.5.dist-info/WHEEL
aequitas_lite-0.43.5.dist-info/entry_points.txt
aequitas_lite-0.43.5.dist-info/top_level.txt
aequitas_lite-0.43.5.dist-info/RECORD
