Metadata-Version: 2.1
Name: aequitas-lite
Version: 0.43.5
Summary: The bias and fairness audit toolkit.
Home-page: https://github.com/dssg/aequitas
Author: Center for Data Science and Public Policy
Author-email: datascifellows@gmail.com
License: https://github.com/dssg/aequitas/blob/master/LICENSE
Keywords: fairness bias aequitas
Platform: UNKNOWN
Classifier: Development Status :: 2 - Pre-Alpha
Classifier: Intended Audience :: Developers
Classifier: License :: OSI Approved :: MIT License
Classifier: Natural Language :: English
Classifier: Programming Language :: Python :: 3
Classifier: Programming Language :: Python :: 3.6
Requires-Dist: matplotlib (>=3.0.3)
Requires-Dist: pandas (>=0.24.1)
Requires-Dist: seaborn (>=0.9.0)
Requires-Dist: altair (>=4.1.0)
Requires-Dist: millify (==0.1.1)
Requires-Dist: scipy (>=0.18.1)
